LICENSE
README.md
pyproject.toml
system_helpers/__init__.py
system_helpers.egg-info/PKG-INFO
system_helpers.egg-info/SOURCES.txt
system_helpers.egg-info/dependency_links.txt
system_helpers.egg-info/entry_points.txt
system_helpers.egg-info/requires.txt
system_helpers.egg-info/top_level.txt
system_helpers/apt/__init__.py
system_helpers/apt/extract.py
system_helpers/apt/install.py
system_helpers/apt/script.py
system_helpers/update_alternatives/__init__.py
system_helpers/update_alternatives/alternatives.py
system_helpers/update_alternatives/argparse_helpers.py
system_helpers/update_alternatives/script.py