Metadata-Version: 2.4
Name: system-helpers
Version: 0.0.3.post4
Summary: Helper scripts for Linux systems.
Author: Arnst Maarten, Tomasetti Romin
License-Expression: MIT
Project-URL: Homepage, https://github.com/uliegecsm/system-helpers
Project-URL: Documentation, https://uliegecsm.github.io/system-helpers/
Requires-Python: >=3.10
License-File: LICENSE
Requires-Dist: typeguard
Dynamic: license-file
